totalcorner/__init__.py
totalcorner/client.py
totalcorner/exceptions.py
totalcorner-0.1.2.dist-info/LICENSE
totalcorner-0.1.2.dist-info/METADATA
totalcorner-0.1.2.dist-info/WHEEL
totalcorner-0.1.2.dist-info/top_level.txt
totalcorner-0.1.2.dist-info/RECORD
