Metadata-Version: 2.1
Name: totalcorner
Version: 0.1.2
Summary: totalcorner.com api client
Home-page: UNKNOWN
Author: jim zhou
Author-email: UNKNOWN
License: MIT
Platform: UNKNOWN
Classifier: Programming Language :: Python
Classifier: Programming Language :: Python :: 3.6
Requires-Dist: requests
